broote/__init__.py
broote/_multi_runner.py
broote/_runner.py
broote/_util.py
broote/exceptions.py
broote-0.6.1.dist-info/LICENSE
broote-0.6.1.dist-info/METADATA
broote-0.6.1.dist-info/WHEEL
broote-0.6.1.dist-info/top_level.txt
broote-0.6.1.dist-info/RECORD
