Metadata-Version: 2.1
Name: broote
Version: 0.6.1
Summary: General purpose python bruteforce library built on top of perock
Home-page: https://github.com/sekgobela-kevin/broote
Author: Sekgobela Kevin
Author-email: kevinnoko23@gmail.com
Project-URL: Bug Tracker, https://github.com/sekgobela-kevin/broote/issues
Keywords: security,bruteforce,hacking,testing
Classifier: Intended Audience :: Developers
Classifier: Development Status :: 2 - Pre-Alpha
Classifier: License :: OSI Approved :: GNU General Public License v3 (GPLv3)
Classifier: Programming Language :: Python
Classifier: Programming Language :: Python :: 3
Classifier: Topic :: Security
Classifier: Topic :: Software Development
Classifier: Topic :: Software Development :: Libraries
Classifier: Topic :: Software Development :: Libraries :: Python Modules
Requires-Python: >=3.6
License-File: LICENSE
Requires-Dist: forcetable (<0.1.0,>=0.0.4)
Requires-Dist: perock (<0.3.0,>=0.1.0)
